iris_magic/__init__.py
iris_magic/iris_magic.py
ipython_iris_magic-0.0.8.dist-info/LICENSE
ipython_iris_magic-0.0.8.dist-info/METADATA
ipython_iris_magic-0.0.8.dist-info/WHEEL
ipython_iris_magic-0.0.8.dist-info/top_level.txt
ipython_iris_magic-0.0.8.dist-info/RECORD
