Metadata-Version: 2.1
Name: ipython-iris-magic
Version: 0.0.8
Summary: ipython-iris-magic
Home-page: https://github.com/grongierisc/ipython-iris-magic
Author: grongier
Author-email: guillaume.rongier@intersystems.com
License: MIT
Keywords: ipython-iris-magic
Classifier: Development Status :: 5 - Production/Stable
Classifier: Intended Audience :: Developers
Classifier: License :: OSI Approved :: MIT License
Classifier: Operating System :: OS Independent
Classifier: Programming Language :: Python :: 3.7
Classifier: Programming Language :: Python :: 3.8
Classifier: Programming Language :: Python :: 3.9
Classifier: Programming Language :: Python :: 3.10
Classifier: Programming Language :: Python :: 3.11
Classifier: Topic :: Utilities
Requires-Python: >=3.9
License-File: LICENSE
Requires-Dist: ipython >=1.0
Requires-Dist: ipython-genutils >=0.1.0
Requires-Dist: sqlalchemy-iris >=0.4.0
